{
  "schema_version": "1.0",
  "task_surface": "smoothing_diagnosis",
  "tool": "variance_audit",
  "version": "1.0",
  "available": true,
  "target": {
    "path": "intermediate/chapters/chapter_two.txt",
    "words": 6390,
    "preprocessing": {
      "applied": true,
      "opt_out": false,
      "rules_active": [
        "yaml_front_matter",
        "html_block",
        "fenced_code",
        "indented_code",
        "inline_code",
        "css_at_rule",
        "css_rule_block",
        "html_tag",
        "json_block",
        "ascii_table"
      ],
      "masking_rules_active": [],
      "input_tokens_before": 6429,
      "input_tokens_after": 6429,
      "tokens_stripped": 0,
      "tokens_stripped_by_rule": {},
      "tokens_masked": 0,
      "strip_ratio": 0.0,
      "dominant_rule": null,
      "warning": null
    }
  },
  "baseline": null,
  "results": {
    "audit": {
      "preprocessing": {
        "applied": true,
        "opt_out": false,
        "rules_active": [
          "yaml_front_matter",
          "html_block",
          "fenced_code",
          "indented_code",
          "inline_code",
          "css_at_rule",
          "css_rule_block",
          "html_tag",
          "json_block",
          "ascii_table"
        ],
        "masking_rules_active": [],
        "input_tokens_before": 6429,
        "input_tokens_after": 6429,
        "tokens_stripped": 0,
        "tokens_stripped_by_rule": {},
        "tokens_masked": 0,
        "strip_ratio": 0.0,
        "dominant_rule": null,
        "warning": null
      },
      "summary": {
        "n_words": 6390,
        "n_words_original": 6429,
        "n_sentences": 240,
        "reliable": true,
        "preprocessing_applied": true
      },
      "tier1": {
        "sentence_length": {
          "n_sentences": 240,
          "mean": 26.625,
          "sd": 22.151461317342562,
          "min": 0.0,
          "max": 115.0,
          "variance": 490.68723849372384,
          "burstiness_B": -0.09171511343457919
        },
        "mattr": {
          "window": 50,
          "value": 0.7988613783315237
        },
        "mtld": 84.69338159255429,
        "yules_k": 137.35272004134004,
        "shannon_entropy_bits": 8.503834485620827,
        "fkgl": {
          "mean": 17.624711644425933,
          "sd": 8.500621454365982,
          "min": -3.3999999999999986,
          "max": 50.08956521739131,
          "n": 197
        },
        "connective_density": {
          "count": 34,
          "per_1000_tokens": 5.320813771517996,
          "by_marker": {
            "consequently": 2,
            "indeed": 7,
            "furthermore": 1,
            "in addition": 1,
            "moreover": 2,
            "therefore": 4,
            "however": 3,
            "particularly": 5,
            "in fact": 1,
            "in conclusion": 1,
            "in other words": 1,
            "thus": 3,
            "namely": 3
          }
        },
        "function_words": {
          "top_n": 100,
          "frequencies": {
            "the": 0.07261345852895149,
            "of": 0.05054773082942097,
            "and": 0.04491392801251956,
            "to": 0.03176838810641627,
            "in": 0.02190923317683881,
            "that": 0.019874804381846637,
            "a": 0.018309859154929577,
            "is": 0.01705790297339593,
            "this": 0.01001564945226917,
            "for": 0.008763693270735524,
            "as": 0.008294209702660408,
            "it": 0.008137715179968702,
            "or": 0.007042253521126761,
            "are": 0.006729264475743349,
            "not": 0.006729264475743349,
            "we": 0.005790297339593114,
            "by": 0.005790297339593114,
            "with": 0.005633802816901409,
            "be": 0.005164319248826291,
            "their": 0.004225352112676056,
            "on": 0.004068857589984351,
            "our": 0.003912363067292645,
            "but": 0.003755868544600939,
            "us": 0.0035993740219092333,
            "which": 0.0035993740219092333,
            "they": 0.0034428794992175274,
            "from": 0.0032863849765258214,
            "when": 0.0032863849765258214,
            "an": 0.003129890453834116,
            "one": 0.00297339593114241,
            "those": 0.0026604068857589984,
            "at": 0.0025039123630672924,
            "all": 0.0025039123630672924,
            "its": 0.002347417840375587,
            "must": 0.0020344287949921754,
            "who": 0.0020344287949921754,
            "these": 0.0018779342723004694,
            "so": 0.0018779342723004694,
            "each": 0.0018779342723004694,
            "them": 0.0018779342723004694,
            "more": 0.0018779342723004694,
            "his": 0.0018779342723004694,
            "being": 0.0018779342723004694,
            "has": 0.0018779342723004694,
            "have": 0.0017214397496087637,
            "will": 0.001564945226917058,
            "only": 0.001564945226917058,
            "if": 0.001564945226917058,
            "own": 0.001564945226917058,
            "i": 0.0014084507042253522,
            "between": 0.0014084507042253522,
            "same": 0.0012519561815336462,
            "her": 0.0012519561815336462,
            "such": 0.0012519561815336462,
            "other": 0.0010954616588419405,
            "just": 0.0010954616588419405,
            "into": 0.0010954616588419405,
            "him": 0.0010954616588419405,
            "up": 0.0010954616588419405,
            "most": 0.0009389671361502347,
            "both": 0.0009389671361502347,
            "does": 0.0009389671361502347,
            "no": 0.0009389671361502347,
            "there": 0.0009389671361502347,
            "been": 0.0009389671361502347,
            "while": 0.0009389671361502347,
            "through": 0.0009389671361502347,
            "would": 0.000782472613458529,
            "very": 0.000782472613458529,
            "because": 0.000782472613458529,
            "nor": 0.000782472613458529,
            "out": 0.000782472613458529,
            "should": 0.000782472613458529,
            "what": 0.0006259780907668231,
            "having": 0.0006259780907668231,
            "any": 0.0006259780907668231,
            "then": 0.0006259780907668231,
            "some": 0.00046948356807511736,
            "themselves": 0.00046948356807511736,
            "about": 0.00046948356807511736,
            "do": 0.00046948356807511736,
            "were": 0.00046948356807511736,
            "he": 0.00046948356807511736,
            "yet": 0.00046948356807511736,
            "few": 0.00046948356807511736,
            "again": 0.00031298904538341156,
            "how": 0.00031298904538341156,
            "my": 0.00031298904538341156,
            "itself": 0.00031298904538341156,
            "over": 0.00031298904538341156,
            "than": 0.00031298904538341156,
            "here": 0.00031298904538341156,
            "once": 0.00015649452269170578,
            "am": 0.00015649452269170578,
            "further": 0.00015649452269170578,
            "had": 0.00015649452269170578,
            "might": 0.00015649452269170578,
            "after": 0.00015649452269170578,
            "could": 0.00015649452269170578,
            "upon": 0.00015649452269170578
          },
          "function_word_ratio": 0.46619718309859154
        }
      },
      "tier2": {
        "available": true,
        "pos_bigrams": {
          "n_bigrams": 7045,
          "n_unique": 181,
          "entropy_bits": 6.103081105473353,
          "top_20": {
            "NOUN-PUNCT": 467,
            "ADJ-NOUN": 445,
            "NOUN-ADP": 441,
            "DET-NOUN": 386,
            "ADP-DET": 343,
            "ADP-NOUN": 226,
            "DET-ADJ": 222,
            "VERB-ADP": 190,
            "NOUN-CCONJ": 176,
            "VERB-DET": 127,
            "AUX-VERB": 122,
            "PRON-VERB": 115,
            "PRON-AUX": 105,
            "PART-VERB": 105,
            "ADP-ADJ": 103,
            "NOUN-AUX": 101,
            "PUNCT-NOUN": 98,
            "NOUN-VERB": 94,
            "CCONJ-NOUN": 93,
            "PROPN-PROPN": 85
          },
          "counts": {
            "PROPN-NUM": 20,
            "NUM-PROPN": 6,
            "PROPN-CCONJ": 15,
            "CCONJ-NOUN": 93,
            "NOUN-ADP": 441,
            "ADP-DET": 343,
            "DET-PROPN": 69,
            "PROPN-NOUN": 3,
            "NUM-PUNCT": 58,
            "PROPN-PROPN": 85,
            "PROPN-ADP": 20,
            "PROPN-AUX": 16,
            "AUX-DET": 30,
            "DET-VERB": 15,
            "VERB-NOUN": 83,
            "NOUN-PUNCT": 467,
            "PUNCT-ADP": 38,
            "ADP-NOUN": 226,
            "PUNCT-NOUN": 98,
            "NOUN-CCONJ": 176,
            "DET-ADJ": 222,
            "ADJ-NOUN": 445,
            "PUNCT-PRON": 73,
            "PRON-VERB": 115,
            "VERB-DET": 127,
            "DET-NOUN": 386,
            "NOUN-NOUN": 32,
            "ADP-ADJ": 103,
            "PRON-AUX": 105,
            "AUX-AUX": 19,
            "AUX-VERB": 122,
            "NOUN-PRON": 56,
            "AUX-ADJ": 24,
            "ADJ-ADP": 35,
            "ADP-VERB": 45,
            "ADJ-CCONJ": 52,
            "CCONJ-ADJ": 70,
            "NOUN-ADV": 19,
            "ADV-NOUN": 7,
            "VERB-PART": 29,
            "PART-VERB": 105,
            "VERB-ADP": 190,
            "ADP-PRON": 81,
            "PRON-ADP": 20,
            "PROPN-PART": 14,
            "PART-PROPN": 3,
            "PROPN-PRON": 4,
            "VERB-PRON": 81,
            "PRON-PART": 11,
            "DET-PUNCT": 12,
            "PUNCT-ADJ": 53,
            "PRON-NOUN": 50,
            "PUNCT-ADV": 42,
            "ADV-ADP": 34,
            "NOUN-PART": 46,
            "VERB-SCONJ": 39,
            "SCONJ-NOUN": 19,
            "AUX-ADV": 34,
            "ADV-ADV": 19,
            "ADV-VERB": 47,
            "PUNCT-DET": 52,
            "ADJ-SCONJ": 11,
            "SCONJ-DET": 43,
            "NOUN-VERB": 94,
            "SCONJ-PRON": 42,
            "VERB-ADV": 28,
            "ADV-PUNCT": 42,
            "PUNCT-SCONJ": 28,
            "SCONJ-SCONJ": 12,
            "VERB-ADJ": 43,
            "ADP-CCONJ": 4,
            "CCONJ-VERB": 69,
            "ADJ-PUNCT": 48,
            "NOUN-AUX": 101,
            "AUX-PUNCT": 11,
            "ADV-CCONJ": 8,
            "CCONJ-ADV": 22,
            "PUNCT-PART": 7,
            "PRON-ADJ": 31,
            "VERB-PROPN": 6,
            "PART-NOUN": 17,
            "PUNCT-CCONJ": 58,
            "CCONJ-PART": 6,
            "ADJ-PART": 9,
            "PART-ADV": 14,
            "VERB-CCONJ": 41,
            "PART-ADJ": 10,
            "ADP-PROPN": 39,
            "PROPN-DET": 3,
            "PROPN-VERB": 33,
            "PROPN-PUNCT": 46,
            "PUNCT-VERB": 67,
            "PRON-PUNCT": 25,
            "PUNCT-PROPN": 13,
            "CCONJ-PROPN": 5,
            "PUNCT-AUX": 16,
            "CCONJ-ADP": 24,
            "NOUN-SCONJ": 23,
            "VERB-PUNCT": 52,
            "CCONJ-PUNCT": 3,
            "ADV-PRON": 4,
            "AUX-PART": 37,
            "PUNCT-NUM": 13,
            "PROPN-SCONJ": 1,
            "SCONJ-PROPN": 5,
            "PRON-ADV": 11,
            "ADV-ADJ": 41,
            "PRON-DET": 12,
            "CCONJ-DET": 39,
            "PUNCT-PUNCT": 26,
            "PRON-PRON": 18,
            "CCONJ-PRON": 23,
            "ADP-NUM": 10,
            "ADJ-ADJ": 35,
            "NUM-SYM": 2,
            "SYM-NUM": 2,
            "ADJ-PROPN": 8,
            "NOUN-NUM": 14,
            "SCONJ-PUNCT": 9,
            "PRON-CCONJ": 10,
            "ADP-ADP": 10,
            "VERB-NUM": 7,
            "NUM-ADP": 3,
            "ADJ-DET": 1,
            "ADP-AUX": 8,
            "PART-AUX": 11,
            "CCONJ-AUX": 7,
            "ADV-AUX": 5,
            "ADV-DET": 15,
            "DET-ADV": 13,
            "PRON-PROPN": 2,
            "AUX-CCONJ": 2,
            "AUX-PRON": 4,
            "NOUN-DET": 5,
            "ADV-PROPN": 1,
            "NUM-NOUN": 6,
            "ADV-SCONJ": 9,
            "PROPN-ADV": 4,
            "AUX-NUM": 1,
            "PART-DET": 4,
            "PUNCT-INTJ": 1,
            "ADJ-AUX": 3,
            "NUM-ADV": 1,
            "AUX-SCONJ": 1,
            "SCONJ-ADJ": 9,
            "AUX-ADP": 5,
            "PART-PART": 2,
            "ADP-SCONJ": 1,
            "AUX-NOUN": 3,
            "VERB-VERB": 9,
            "NUM-PART": 5,
            "SCONJ-AUX": 1,
            "ADP-PUNCT": 8,
            "CCONJ-SCONJ": 5,
            "SCONJ-ADV": 2,
            "PART-ADP": 3,
            "ADJ-VERB": 2,
            "PART-PUNCT": 1,
            "ADP-ADV": 6,
            "PRON-SCONJ": 5,
            "DET-PRON": 1,
            "DET-DET": 2,
            "SCONJ-VERB": 4,
            "ADJ-PRON": 1,
            "SCONJ-PART": 2,
            "SCONJ-CCONJ": 1,
            "NOUN-PROPN": 2,
            "ADJ-ADV": 3,
            "ADV-PART": 3,
            "NOUN-ADJ": 3,
            "VERB-X": 1,
            "X-X": 2,
            "X-NOUN": 2,
            "PUNCT-X": 1,
            "NUM-DET": 1,
            "ADV-NUM": 1,
            "NUM-ADJ": 1,
            "DET-NUM": 1,
            "PROPN-ADJ": 1,
            "PART-PRON": 1,
            "CCONJ-NUM": 2
          }
        },
        "mdd": {
          "n_sentences": 230,
          "mean": 3.1768465142199616,
          "sd": 0.9731498702609622
        }
      }
    },
    "compression": {
      "band": "Lightly smoothed",
      "weighted_score": 0.0,
      "available_weight": 11.0,
      "compression_fraction": 0.0,
      "flagged_signals": [],
      "available_signals": [
        "burstiness_B",
        "sentence_length_sd",
        "connective_density",
        "mattr",
        "mtld",
        "yules_k",
        "shannon_entropy",
        "fkgl_sd",
        "mdd_sd"
      ],
      "skipped_signals": [],
      "n_flagged": 0,
      "notes": {},
      "thresholds_used": {
        "burstiness_B": {
          "threshold": -0.4,
          "direction": "lt",
          "direction_used": "lt",
          "direction_by_comparator": null,
          "direction_by_comparator_and_slice": null,
          "comparator_class": null,
          "judge": null,
          "generator": null,
          "weight": 2.0,
          "length_floor": 200,
          "signal_path": "tier1.sentence_length.burstiness_B",
          "provenance": "editlens_v1_findings_2026-05-10",
          "status": "empirically_oriented",
          "provisional": true
        },
        "connective_density": {
          "threshold": 20.0,
          "direction": "gt",
          "direction_used": "gt",
          "direction_by_comparator": null,
          "direction_by_comparator_and_slice": null,
          "comparator_class": null,
          "judge": null,
          "generator": null,
          "weight": 2.0,
          "length_floor": 200,
          "signal_path": "tier1.connective_density.per_1000_tokens",
          "provenance": "editlens_v1_findings_2026-05-10",
          "status": "empirically_oriented",
          "provisional": true
        },
        "mattr": {
          "threshold": 0.65,
          "direction": "lt",
          "direction_used": "lt",
          "direction_by_comparator": null,
          "direction_by_comparator_and_slice": null,
          "comparator_class": null,
          "judge": null,
          "generator": null,
          "weight": 1.0,
          "length_floor": 300,
          "signal_path": "tier1.mattr.value",
          "provenance": "mattr_literary_fiction_baseline_window_50",
          "status": "literature_anchored",
          "provisional": true
        },
        "mtld": {
          "threshold": 60.0,
          "direction": "lt",
          "direction_used": "lt",
          "direction_by_comparator": null,
          "direction_by_comparator_and_slice": null,
          "comparator_class": null,
          "judge": null,
          "generator": null,
          "weight": 1.0,
          "length_floor": 500,
          "signal_path": "tier1.mtld",
          "provenance": null,
          "status": "heuristic",
          "provisional": true
        },
        "yules_k": {
          "threshold": 200.0,
          "direction": "gt",
          "direction_used": "gt",
          "direction_by_comparator": null,
          "direction_by_comparator_and_slice": null,
          "comparator_class": null,
          "judge": null,
          "generator": null,
          "weight": 1.0,
          "length_floor": 500,
          "signal_path": "tier1.yules_k",
          "provenance": null,
          "status": "heuristic",
          "provisional": true
        },
        "shannon_entropy": {
          "threshold": 7.0,
          "direction": "lt",
          "direction_used": "lt",
          "direction_by_comparator": null,
          "direction_by_comparator_and_slice": null,
          "comparator_class": null,
          "judge": null,
          "generator": null,
          "weight": 1.0,
          "length_floor": 2000,
          "signal_path": "tier1.shannon_entropy_bits",
          "provenance": "shannon_entropy_native_fiction_literature",
          "status": "literature_anchored",
          "provisional": true
        },
        "fkgl_sd": {
          "threshold": 1.5,
          "direction": "lt",
          "direction_used": "lt",
          "direction_by_comparator": null,
          "direction_by_comparator_and_slice": null,
          "comparator_class": null,
          "judge": null,
          "generator": null,
          "weight": 1.5,
          "length_floor": 200,
          "signal_path": "tier1.fkgl.sd",
          "provenance": "editlens_v1_findings_2026-05-10",
          "status": "empirically_oriented",
          "provisional": true
        },
        "sentence_length_sd": {
          "threshold": 5.0,
          "direction": "lt",
          "direction_used": "lt",
          "direction_by_comparator": null,
          "direction_by_comparator_and_slice": null,
          "comparator_class": null,
          "judge": null,
          "generator": null,
          "weight": 0.5,
          "length_floor": 5000,
          "signal_path": "tier1.sentence_length.sd",
          "provenance": "editlens_v1_findings_2026-05-10",
          "status": "empirically_oriented",
          "provisional": true
        },
        "adjacent_cosine_mean": {
          "threshold": 0.6,
          "direction": "lt",
          "direction_used": "lt",
          "direction_by_comparator": null,
          "direction_by_comparator_and_slice": null,
          "comparator_class": null,
          "judge": null,
          "generator": null,
          "weight": 1.5,
          "length_floor": 200,
          "signal_path": "tier3.adjacent_cosine.mean",
          "provenance": "mage_5k_polarity_audit_2026-05-18",
          "status": "empirically_oriented",
          "provisional": true
        },
        "adjacent_cosine_sd": {
          "threshold": 0.12,
          "direction": "lt",
          "direction_used": "lt",
          "direction_by_comparator": null,
          "direction_by_comparator_and_slice": null,
          "comparator_class": null,
          "judge": null,
          "generator": null,
          "weight": 1.0,
          "length_floor": 300,
          "signal_path": "tier3.adjacent_cosine.sd",
          "provenance": "editlens_v1_findings_2026-05-10",
          "status": "empirically_oriented",
          "provisional": true
        },
        "mdd_sd": {
          "threshold": 0.7,
          "direction": "lt",
          "direction_used": "lt",
          "direction_by_comparator": null,
          "direction_by_comparator_and_slice": null,
          "comparator_class": null,
          "judge": null,
          "generator": null,
          "weight": 1.0,
          "length_floor": 300,
          "signal_path": "tier2.mdd.sd",
          "provenance": "editlens_v1_findings_2026-05-10",
          "status": "empirically_oriented",
          "provisional": true
        },
        "surprisal_mean": {
          "threshold": 3.5,
          "direction": "gt",
          "direction_used": "gt",
          "direction_by_comparator": null,
          "direction_by_comparator_and_slice": null,
          "comparator_class": null,
          "judge": null,
          "generator": null,
          "weight": 1.5,
          "length_floor": 300,
          "signal_path": "tier4.surprisal.mean",
          "provenance": "mage_5k_polarity_audit_2026-05-18",
          "status": "empirically_oriented",
          "provisional": true
        },
        "surprisal_sd": {
          "threshold": 1.5,
          "direction": "gt",
          "direction_used": "gt",
          "direction_by_comparator": {
            "raid": "lt"
          },
          "direction_by_comparator_and_slice": null,
          "comparator_class": null,
          "judge": null,
          "generator": null,
          "weight": 2.0,
          "length_floor": 300,
          "signal_path": "tier4.surprisal.sd",
          "provenance": "mage_5k_polarity_audit_2026-05-18",
          "status": "empirically_oriented",
          "provisional": true
        },
        "surprisal_acf_lag1": {
          "threshold": 0.3,
          "direction": "lt",
          "direction_used": "lt",
          "direction_by_comparator": null,
          "direction_by_comparator_and_slice": null,
          "comparator_class": null,
          "judge": null,
          "generator": null,
          "weight": 1.0,
          "length_floor": 500,
          "signal_path": "tier4.surprisal.autocorrelation.lag_1",
          "provenance": "mage_5k_polarity_audit_2026-05-18",
          "status": "empirically_oriented",
          "provisional": true
        },
        "correctio_density": {
          "threshold": 12.0,
          "direction": "gt",
          "direction_used": "gt",
          "direction_by_comparator": null,
          "direction_by_comparator_and_slice": null,
          "comparator_class": null,
          "judge": null,
          "generator": null,
          "weight": 1.0,
          "length_floor": 400,
          "signal_path": "patterns.correctio.density_per_1k",
          "provenance": null,
          "status": "heuristic",
          "provisional": true
        },
        "triplet_density": {
          "threshold": 8.0,
          "direction": "gt",
          "direction_used": "gt",
          "direction_by_comparator": null,
          "direction_by_comparator_and_slice": null,
          "comparator_class": null,
          "judge": null,
          "generator": null,
          "weight": 1.0,
          "length_floor": 400,
          "signal_path": "patterns.triplet.density_per_1k",
          "provenance": null,
          "status": "heuristic",
          "provisional": true
        },
        "manifesto_cadence_density": {
          "threshold": 3.0,
          "direction": "gt",
          "direction_used": "gt",
          "direction_by_comparator": null,
          "direction_by_comparator_and_slice": null,
          "comparator_class": null,
          "judge": null,
          "generator": null,
          "weight": 1.0,
          "length_floor": 400,
          "signal_path": "patterns.manifesto_cadence.density_per_1k",
          "provenance": null,
          "status": "heuristic",
          "provisional": true
        },
        "professional_parallel_stack_density": {
          "threshold": 2.0,
          "direction": "gt",
          "direction_used": "gt",
          "direction_by_comparator": null,
          "direction_by_comparator_and_slice": null,
          "comparator_class": null,
          "judge": null,
          "generator": null,
          "weight": 1.0,
          "length_floor": 400,
          "signal_path": "patterns.professional_parallel_stack.density_per_1k",
          "provenance": null,
          "status": "heuristic",
          "provisional": true
        },
        "kicker_density": {
          "threshold": 0.25,
          "direction": "gt",
          "direction_used": "gt",
          "direction_by_comparator": null,
          "direction_by_comparator_and_slice": null,
          "comparator_class": null,
          "judge": null,
          "generator": null,
          "weight": 1.0,
          "length_floor": 400,
          "signal_path": "aic_8_9.kicker_density.value",
          "provenance": null,
          "status": "heuristic",
          "provisional": true
        },
        "image_conjunction_density": {
          "threshold": 15.0,
          "direction": "gt",
          "direction_used": "gt",
          "direction_by_comparator": null,
          "direction_by_comparator_and_slice": null,
          "comparator_class": null,
          "judge": null,
          "generator": null,
          "weight": 1.0,
          "length_floor": 400,
          "signal_path": "aic_8_9.image_conjunction_density.value",
          "provenance": null,
          "status": "heuristic",
          "provisional": true
        },
        "prestige_metaphor_scatter": {
          "threshold": 0.7,
          "direction": "gt",
          "direction_used": "gt",
          "direction_by_comparator": null,
          "direction_by_comparator_and_slice": null,
          "comparator_class": null,
          "judge": null,
          "generator": null,
          "weight": 1.0,
          "length_floor": 400,
          "signal_path": "aic_8_9.prestige_metaphor_density.domain_scatter_entropy",
          "provenance": null,
          "status": "heuristic",
          "provisional": true
        },
        "pos_bigram_kl": {
          "threshold": 0.15,
          "direction": "gt",
          "weight": 2.0,
          "length_floor": 500,
          "signal_path": "baseline_divergences.pos_bigrams.kl",
          "provenance": "pos_bigram_kl_distributional_diagnostics",
          "status": "literature_anchored",
          "provisional": true,
          "requires_baseline": true
        }
      },
      "calibration_status": {
        "n_calibrated": 0,
        "n_provisional": 21,
        "n_total": 21,
        "calibrated_signals": [],
        "provisional_signals": [
          "burstiness_B",
          "connective_density",
          "mattr",
          "mtld",
          "yules_k",
          "shannon_entropy",
          "fkgl_sd",
          "sentence_length_sd",
          "adjacent_cosine_mean",
          "adjacent_cosine_sd",
          "mdd_sd",
          "surprisal_mean",
          "surprisal_sd",
          "surprisal_acf_lag1",
          "correctio_density",
          "triplet_density",
          "manifesto_cadence_density",
          "professional_parallel_stack_density",
          "kicker_density",
          "image_conjunction_density",
          "prestige_metaphor_scatter"
        ]
      }
    }
  },
  "claim_license": {
    "task_surface": "smoothing_diagnosis",
    "licenses": "Layer A distributional diagnostic. Reports per-tier stylometric signals (Tier 1 variance: sentence-length SD / MATTR / MTLD / Yule's K / Shannon entropy / FKGL SD / connective density / function-word ratio; Tier 2 syntax: POS-bigram entropy + KL / MDD SD; Tier 3 trajectory: adjacent-sentence cosine mean and SD; Tier 4 surprisal when --tier4 is supplied) plus a compression-band classification. When --baseline-dir is supplied, also reports per-signal z-scores and distributional divergences. Sliding-window mode (--window-size) localizes compression within a long document.",
    "does_not_license": "An authorship verdict. Distributional smoothing has many causes \u2014 RLHF mode collapse is ONE of them, but so are genre conventions, professional copyediting, register shift, ESL writing, translation cleanup, intentional voice imitation, time drift, and POV collapse. Bands are heuristic-tier with empirically-oriented anchors on six Tier 1 signals (2026-05-10 EditLens findings); thresholds do not generalize across corpora (see ROADMAP.md cross-corpus polarity inversion). The audit does NOT license a claim that a draft is AI-generated based on compression alone.",
    "comparison_set": {
      "n_words": 6390,
      "n_sentences": 240,
      "band": "Lightly smoothed",
      "has_baseline": false,
      "windowed": false
    },
    "length_range_words": null,
    "register_match": [],
    "language_match": [],
    "fpr_target": null,
    "confidence_interval_95": null,
    "additional_caveats": [
      "Tier 1-3 signals carry mixed calibration status; see references/signals-glossary.md for per-signal status (heuristic / literature_anchored / empirically_oriented). Calibrated thresholds are not shipped as load-bearing defaults per the Stylometry-to-the-people policy.",
      "Without a personal baseline, signals fire against general-prose heuristic thresholds that may not generalize to the writer's register. Always run with --baseline-dir when a register-matched baseline is available.",
      "Sliding-window mode localizes compression but inherits the same heuristic-tier thresholds at the window level; interpret window bands as cues, not verdicts."
    ],
    "references": []
  },
  "claim_license_rendered": "## What this result licenses\n\n**Task surface:** AI-prose smoothing diagnosis\n\n**Reports:** Layer A distributional diagnostic. Reports per-tier stylometric signals (Tier 1 variance: sentence-length SD / MATTR / MTLD / Yule's K / Shannon entropy / FKGL SD / connective density / function-word ratio; Tier 2 syntax: POS-bigram entropy + KL / MDD SD; Tier 3 trajectory: adjacent-sentence cosine mean and SD; Tier 4 surprisal when --tier4 is supplied) plus a compression-band classification. When --baseline-dir is supplied, also reports per-signal z-scores and distributional divergences. Sliding-window mode (--window-size) localizes compression within a long document.\n\n**Does NOT report:** An authorship verdict. Distributional smoothing has many causes \u2014 RLHF mode collapse is ONE of them, but so are genre conventions, professional copyediting, register shift, ESL writing, translation cleanup, intentional voice imitation, time drift, and POV collapse. Bands are heuristic-tier with empirically-oriented anchors on six Tier 1 signals (2026-05-10 EditLens findings); thresholds do not generalize across corpora (see ROADMAP.md cross-corpus polarity inversion). The audit does NOT license a claim that a draft is AI-generated based on compression alone.\n\n### Comparison context\n\n- **band:** Lightly smoothed\n- **has baseline:** False\n- **n sentences:** 240\n- **n words:** 6390\n- **windowed:** False\n\n### Caveats\n\n- Tier 1-3 signals carry mixed calibration status; see references/signals-glossary.md for per-signal status (heuristic / literature_anchored / empirically_oriented). Calibrated thresholds are not shipped as load-bearing defaults per the Stylometry-to-the-people policy.\n- Without a personal baseline, signals fire against general-prose heuristic thresholds that may not generalize to the writer's register. Always run with --baseline-dir when a register-matched baseline is available.\n- Sliding-window mode localizes compression but inherits the same heuristic-tier thresholds at the window level; interpret window bands as cues, not verdicts.",
  "warnings": [],
  "ai_status": null
}
